sde_bbdm/.DS_Store
sde_bbdm/__init__.py
sde_bbdm/callbacks/__init__.py
sde_bbdm/callbacks/lr.py
sde_bbdm/configs/__init__.py
sde_bbdm/configs/eval.py
sde_bbdm/configs/train.py
sde_bbdm/managers/__init__.py
sde_bbdm/managers/bbdm.py
sde_bbdm/managers/latent.py
sde_bbdm/managers/ldm.py
sde_bbdm/managers/sde_bbdm.py
sde_bbdm/networks/__init__.py
sde_bbdm/networks/builder.py
sde_bbdm/networks/openai.py
sde_bbdm/networks/utils.py
sde_bbdm/nn/__init__.py
sde_bbdm/nn/a_bridge.py
sde_bbdm/nn/bbdm.py
sde_bbdm/version.py
sde_bbdm-1.1.dist-info/LICENSE
sde_bbdm-1.1.dist-info/METADATA
sde_bbdm-1.1.dist-info/WHEEL
sde_bbdm-1.1.dist-info/RECORD
