Metadata-Version: 2.3
Name: sde_bbdm
Version: 1.1
Summary: Score-Based Image-to-Image Brownian Bridge (v1.1)
Requires-Python: >=3.9,<4.0
Classifier: Programming Language :: Python :: 3
Classifier: Programming Language :: Python :: 3.9
Classifier: Programming Language :: Python :: 3.10
Classifier: Programming Language :: Python :: 3.11
Classifier: Programming Language :: Python :: 3.12
Classifier: Programming Language :: Python :: 3.13
Requires-Dist: einops (>=0.6.1,<0.7.0)
Requires-Dist: lpips (>=0.1.4,<0.2.0)
Requires-Dist: torch (>=2.1.2,<3.0.0)
Requires-Dist: torchmanager (>=1.3,<2.0)
Requires-Dist: torchmanager-diffusion (>=1.1,<2.0)
